setup.py
lojbansuggest/__init__.py
lojbansuggest/suggest.py
lojbansuggest/tree.py
lojbansuggest.egg-info/PKG-INFO
lojbansuggest.egg-info/SOURCES.txt
lojbansuggest.egg-info/dependency_links.txt
lojbansuggest.egg-info/requires.txt
lojbansuggest.egg-info/top_level.txt
scripts/
scripts/lojbantreeproj.py
scripts/showlojbantree.sh
scripts/suggest.py