Metadata-Version: 1.0
Name: lojbansuggest
Version: 0.2.2
Summary: UNKNOWN
Home-page: UNKNOWN
Author: Timo Paulssen
Author-email: timo+lojbansuggest@wakelift.de
License: BSD
Download-URL: http://wakelift.de/lojban/software/python/lojbansuggest-0.2.2.tar.gz
Platform: UNKNOWN
Classifier: Development Status :: 3 - Alpha
Classifier: Environment :: Console
Classifier: Intended Audience :: Education
Classifier: Intended Audience :: Developers
Classifier: License :: OSI Approved :: BSD License
Classifier: Operating System :: OS Independent
Classifier: Programming Language :: Python
Classifier: Topic :: Text Processing :: Linguistic
